CHANGES
LICENSE
MANIFEST.in
README.rst
setup.py
rq_monitor/__init__.py
rq_monitor/app.py
rq_monitor.egg-info/PKG-INFO
rq_monitor.egg-info/SOURCES.txt
rq_monitor.egg-info/dependency_links.txt
rq_monitor.egg-info/entry_points.txt
rq_monitor.egg-info/not-zip-safe
rq_monitor.egg-info/requires.txt
rq_monitor.egg-info/top_level.txt
rq_monitor/static/css/bootstrap-responsive.min.css
rq_monitor/static/css/bootstrap.min.css
rq_monitor/static/img/glyphicons-halflings-white.png
rq_monitor/static/img/glyphicons-halflings.png
rq_monitor/static/js/bootstrap.min.js
rq_monitor/static/js/main.js
rq_monitor/templates/index.html