Metadata-Version: 1.0
Name: rq-monitor
Version: 0.1.0
Summary: RQ Monitor - simple RQ dashboard.
Home-page: http://github.com/andrzej-jankowski
Author: Andrzej Jankowski
Author-email: andew.jankowski@gmail.com
License: Apache Software License v2.0
Platform: UNKNOWN
